{
    "classname": "Profile",
    "definitions": {
        "apis": {
            "custom": [],
            "passthrough": []
        },
        "events": {
            "custom": [],
            "passthrough": []
        },
        "groups": {
            "apis": [],
            "events": [],
            "properties": [],
            "widgets": []
        },
        "properties": {
            "custom": [],
            "passthrough": [
                {
                    "access": "Enable",
                    "group": "General",
                    "kuid": "f820fa6b22674d329ab74f20b22ac37b",
                    "originalPropertyKey": "text",
                    "propertyIndex": 1,
                    "propertyKey": "userName",
                    "pw": {
                        "access": "readwrite",
                        "category": "look",
                        "dependentKeysKUIDs": null,
                        "displayName": "userName",
                        "srcWidget": "userName",
                        "type": "string",
                        "uiRepresentation": "Label-Textbox",
                        "wType": "Label"
                    },
                    "srcWgtKUID": "c0a8912c27e54b489e0db96074587dd7"
                },
                {
                    "access": "Enable",
                    "group": "General",
                    "kuid": "g97e1be55647422b8799054ed03c258a",
                    "originalPropertyKey": "text",
                    "propertyIndex": 2,
                    "propertyKey": "userHandle",
                    "pw": {
                        "access": "readwrite",
                        "category": "look",
                        "dependentKeysKUIDs": null,
                        "displayName": "userHandle",
                        "srcWidget": "userNickName",
                        "type": "string",
                        "uiRepresentation": "Label-Textbox",
                        "wType": "Label"
                    },
                    "srcWgtKUID": "bf556484dc09478f918b9f4322004d99"
                },
                {
                    "access": "Enable",
                    "group": "General",
                    "kuid": "g96085c39c9547a08462c990f7cc505d",
                    "originalPropertyKey": "text",
                    "propertyIndex": 3,
                    "propertyKey": "userDescription",
                    "pw": {
                        "access": "readwrite",
                        "category": "look",
                        "dependentKeysKUIDs": null,
                        "displayName": "userDescription",
                        "srcWidget": "lblDescription",
                        "type": "string",
                        "uiRepresentation": "Label-Textbox",
                        "wType": "Label"
                    },
                    "srcWgtKUID": "ff39d6725b084205b7102b8d71106e2d"
                },
                {
                    "access": "Enable",
                    "group": "General",
                    "kuid": "h2a623d4a26e45cdafdfcdf51b9f62b2",
                    "originalPropertyKey": "text",
                    "propertyIndex": 4,
                    "propertyKey": "userLocation",
                    "pw": {
                        "access": "readwrite",
                        "category": "look",
                        "dependentKeysKUIDs": null,
                        "displayName": "userLocation",
                        "srcWidget": "location",
                        "type": "string",
                        "uiRepresentation": "Label-Textbox",
                        "wType": "Label"
                    },
                    "srcWgtKUID": "add0927f76714bab8149477d8d346cf0"
                },
                {
                    "access": "Enable",
                    "group": "General",
                    "kuid": "e2aed375921247929cab1bba7ad4dd57",
                    "originalPropertyKey": "text",
                    "propertyIndex": 5,
                    "propertyKey": "userFollowersNumber",
                    "pw": {
                        "access": "readwrite",
                        "category": "look",
                        "dependentKeysKUIDs": null,
                        "displayName": "userFollowersNumber",
                        "srcWidget": "followersNumber",
                        "type": "string",
                        "uiRepresentation": "Label-Textbox",
                        "wType": "Label"
                    },
                    "srcWgtKUID": "dac1e1524c804bf198e786c5626da46f"
                },
                {
                    "access": "Enable",
                    "group": "General",
                    "kuid": "id90cddf2e84413780b6795d292a3f9d",
                    "originalPropertyKey": "text",
                    "propertyIndex": 6,
                    "propertyKey": "userFollowingNumber",
                    "pw": {
                        "access": "readwrite",
                        "category": "look",
                        "dependentKeysKUIDs": null,
                        "displayName": "userFollowingNumber",
                        "srcWidget": "followingNumber",
                        "type": "string",
                        "uiRepresentation": "Label-Textbox",
                        "wType": "Label"
                    },
                    "srcWgtKUID": "aaed2817ce6b461a85e909323607cb86"
                },
                {
                    "access": "Enable",
                    "group": "General",
                    "kuid": "gef0c178f41e4e3880fb4c1c0fe9140e",
                    "originalPropertyKey": "src",
                    "propertyIndex": 7,
                    "propertyKey": "profilePicSrc",
                    "pw": {
                        "access": "readwrite",
                        "category": "widget",
                        "dependentKeysKUIDs": null,
                        "displayName": "profilePicSrc",
                        "srcWidget": "profileImage",
                        "type": "string",
                        "uiConfig": {
                            "Button": {
                                "dataRetrieverId": "Imagelist",
                                "dataUpdaterId": "Imagelist",
                                "popupId": "Imagelist",
                                "type": "ImageEditBtn"
                            },
                            "Label": {}
                        },
                        "uiRepresentation": "Label-Label-Button",
                        "wType": "Image"
                    },
                    "srcWgtKUID": "eb24cc00ceb247fb8e02899f63ff3a31"
                },
                {
                    "access": "Enable",
                    "group": "General",
                    "kuid": "f6955432e48147f0810cb6f355247db5",
                    "originalPropertyKey": "src",
                    "propertyIndex": 8,
                    "propertyKey": "userCoverPhoto",
                    "pw": {
                        "access": "readwrite",
                        "category": "widget",
                        "dependentKeysKUIDs": null,
                        "displayName": "userCoverPhoto",
                        "srcWidget": "coverPhoto",
                        "type": "string",
                        "uiConfig": {
                            "Button": {
                                "dataRetrieverId": "Imagelist",
                                "dataUpdaterId": "Imagelist",
                                "popupId": "Imagelist",
                                "type": "ImageEditBtn"
                            },
                            "Label": {}
                        },
                        "uiRepresentation": "Label-Label-Button",
                        "wType": "Image"
                    },
                    "srcWgtKUID": "h22139ff8a1744769a9bb7b4b60c5e55"
                },
                {
                    "access": "Enable",
                    "group": "General",
                    "kuid": "f71cbb99f4b047d1a37f888798a867aa",
                    "originalPropertyKey": "isVisible",
                    "propertyIndex": 9,
                    "propertyKey": "isVisible1",
                    "pw": {
                        "access": "readwrite",
                        "category": "look",
                        "displayName": "Visible",
                        "type": "boolean",
                        "uiRepresentation": "Label-Radiobuttongroup",
                        "wType": "Camera"
                    },
                    "srcWgtKUID": "d4419f02c4864ad6b094a040ad80aa8d"
                }
            ]
        },
        "widgets": {
            "expose": [],
            "passthrough": []
        }
    },
    "namespace": "ProfileBio",
    "version": "1.0.0"
}